{
  "name": "売上データ",
  "cells": {
    "A1": {"t": "s", "v": "商品"},
    "B1": {"t": "s", "v": "カテゴリ"},
    "C1": {"t": "s", "v": "数量"},
    "D1": {"t": "s", "v": "金額"},
    "A2": {"t": "s", "v": "りんご"},
    "B2": {"t": "s", "v": "果物"},
    "C2": {"t": "n", "v": 100},
    "D2": {"t": "n", "v": 5000},
    "A3": {"t": "s", "v": "みかん"},
    "B3": {"t": "s", "v": "果物"},
    "C3": {"t": "n", "v": 80},
    "D3": {"t": "n", "v": 3200},
    "A4": {"t": "s", "v": "にんじん"},
    "B4": {"t": "s", "v": "野菜"},
    "C4": {"t": "n", "v": 50},
    "D4": {"t": "n", "v": 1500},
    "A5": {"t": "s", "v": "ぶどう"},
    "B5": {"t": "s", "v": "果物"},
    "C5": {"t": "n", "v": 60},
    "D5": {"t": "n", "v": 4200}
  },
  "autoFilter": "A1:D5",
  "tables": [
    {
      "range": "A1:D5",
      "name": "SalesTable",
      "style": "TableStyleMedium2",
      "bandedRows": true,
      "headerRow": true
    }
  ],
  "freeze": {"row": 1}
}
